eegproc/__init__.py
eegproc/featurization.py
eegproc/preprocessing.py
eegproc-1.0.0.dist-info/licenses/LICENSE
eegproc-1.0.0.dist-info/METADATA
eegproc-1.0.0.dist-info/WHEEL
eegproc-1.0.0.dist-info/top_level.txt
eegproc-1.0.0.dist-info/RECORD
