Metadata-Version: 2.4
Name: eegproc
Version: 1.0.0
Summary: EEG Preprocessing and Featurization Library
Author-email: Tolas <inserra.vitor@gmail.com>
License:                     GNU GENERAL PUBLIC LICENSE
Project-URL: Homepage, https://github.com/VitorInserra/EEGProc
Keywords: eeg,entropy,preprocessing,featurization,neuroscience,vectorization,dataframes
Classifier: License :: OSI Approved :: GNU General Public License v2 (GPLv2)
Classifier: Programming Language :: Python :: 3
Classifier: Programming Language :: Python :: 3.10
Requires-Python: >=3
License-File: LICENSE
Requires-Dist: dill>=0.4.0
Requires-Dist: EMD-signal>=1.6.4
Requires-Dist: joblib>=1.5.2
Requires-Dist: multiprocess>=0.70.18
Requires-Dist: numpy>=2.2.6
Requires-Dist: pandas>=2.3.2
Requires-Dist: pathos>=0.3.4
Requires-Dist: pox>=0.3.6
Requires-Dist: ppft>=1.7.7
Requires-Dist: python-dateutil>=2.9.0.post0
Requires-Dist: pytz>=2025.2
Requires-Dist: PyWavelets>=1.8.0
Requires-Dist: scikit-learn>=1.7.2
Requires-Dist: scipy>=1.15.3
Requires-Dist: six>=1.17.0
Requires-Dist: threadpoolctl>=3.6.0
Requires-Dist: tqdm>=4.67.1
Requires-Dist: tzdata>=2025.2
Dynamic: license-file
